cgse_dummy/__init__.py
cgse_dummy/cgse_explore.py
cgse_dummy/cgse_services.py
cgse_dummy/dummy_acs.py
cgse_dummy/dummy_adev.py
cgse_dummy/dummy_cs.py
cgse_dummy/dummy_dev.py
cgse_dummy/dummy_sim.py
cgse_dummy/scpi.py
cgse_dummy/settings.yaml
cgse_dummy/sim_data.py
cgse_dummy-0.6.6.dist-info/METADATA
cgse_dummy-0.6.6.dist-info/WHEEL
cgse_dummy-0.6.6.dist-info/entry_points.txt
cgse_dummy-0.6.6.dist-info/RECORD
